{"trackId": "training-beat", "title": "Training Beat", "bpm": 120, "offsetMs": 0, "lanes": 4, "durationMs": 20000, "notes": [{"tMs": 1000, "lane": 1}, {"tMs": 1062, "lane": 0}, {"tMs": 1124, "lane": 3}, {"tMs": 1186, "lane": 3}, {"tMs": 1248, "lane": 0}, {"tMs": 1310, "lane": 3}, {"tMs": 1372, "lane": 0}, {"tMs": 1434, "lane": 3}, {"tMs": 1496, "lane": 0}, {"tMs": 1558, "lane": 1}, {"tMs": 1620, "lane": 3}, {"tMs": 1682, "lane": 3}, {"tMs": 1744, "lane": 0}, {"tMs": 1806, "lane": 1}, {"tMs": 1868, "lane": 1}, {"tMs": 1930, "lane": 3}, {"tMs": 1992, "lane": 2}, {"tMs": 2054, "lane": 3}, {"tMs": 2116, "lane": 0}, {"tMs": 2178, "lane": 3}, {"tMs": 2240, "lane": 3}, {"tMs": 2302, "lane": 0}, {"tMs": 2364, "lane": 3}, {"tMs": 2426, "lane": 2}, {"tMs": 2488, "lane": 2}, {"tMs": 2550, "lane": 1}, {"tMs": 2612, "lane": 0}, {"tMs": 2674, "lane": 1}, {"tMs": 2736, "lane": 3}, {"tMs": 2798, "lane": 3}, {"tMs": 2860, "lane": 0}, {"tMs": 2922, "lane": 0}, {"tMs": 2984, "lane": 3}, {"tMs": 3046, "lane": 1}, {"tMs": 3108, "lane": 3}, {"tMs": 3170, "lane": 0}, {"tMs": 3232, "lane": 1}, {"tMs": 3294, "lane": 1}, {"tMs": 3356, "lane": 3}, {"tMs": 3418, "lane": 0}, {"tMs": 3480, "lane": 1}, {"tMs": 3542, "lane": 3}, {"tMs": 3604, "lane": 0}, {"tMs": 3666, "lane": 1}, {"tMs": 3728, "lane": 2}, {"tMs": 3790, "lane": 2}, {"tMs": 3852, "lane": 2}, {"tMs": 3914, "lane": 3}, {"tMs": 3976, "lane": 1}, {"tMs": 4038, "lane": 2}, {"tMs": 4100, "lane": 2}, {"tMs": 4162, "lane": 1}, {"tMs": 4224, "lane": 0}, {"tMs": 4286, "lane": 3}, {"tMs": 4348, "lane": 2}, {"tMs": 4410, "lane": 0}, {"tMs": 4472, "lane": 0}, {"tMs": 4534, "lane": 0}, {"tMs": 4596, "lane": 0}, {"tMs": 4658, "lane": 2}, {"tMs": 4720, "lane": 2}, {"tMs": 4782, "lane": 0}, {"tMs": 4844, "lane": 3}, {"tMs": 4906, "lane": 3}, {"tMs": 4968, "lane": 1}, {"tMs": 5030, "lane": 1}, {"tMs": 5092, "lane": 1}, {"tMs": 5154, "lane": 1}, {"tMs": 5216, "lane": 2}, {"tMs": 5278, "lane": 1}, {"tMs": 5340, "lane": 3}, {"tMs": 5402, "lane": 3}, {"tMs": 5464, "lane": 2}, {"tMs": 5526, "lane": 1}, {"tMs": 5588, "lane": 0}, {"tMs": 5650, "lane": 2}, {"tMs": 5712, "lane": 0}, {"tMs": 5774, "lane": 3}, {"tMs": 5836, "lane": 0}, {"tMs": 5898, "lane": 1}, {"tMs": 5960, "lane": 3}, {"tMs": 6022, "lane": 0}, {"tMs": 6084, "lane": 2}, {"tMs": 6146, "lane": 1}, {"tMs": 6208, "lane": 2}, {"tMs": 6270, "lane": 2}, {"tMs": 6332, "lane": 1}, {"tMs": 6394, "lane": 1}, {"tMs": 6456, "lane": 3}, {"tMs": 6518, "lane": 3}, {"tMs": 6580, "lane": 2}, {"tMs": 6642, "lane": 2}, {"tMs": 6704, "lane": 1}, {"tMs": 6766, "lane": 0}, {"tMs": 6828, "lane": 2}, {"tMs": 6890, "lane": 2}, {"tMs": 6952, "lane": 2}, {"tMs": 7014, "lane": 0}, {"tMs": 7076, "lane": 1}, {"tMs": 7138, "lane": 0}, {"tMs": 7200, "lane": 3}, {"tMs": 7262, "lane": 0}, {"tMs": 7324, "lane": 2}, {"tMs": 7386, "lane": 1}, {"tMs": 7448, "lane": 0}, {"tMs": 7510, "lane": 3}, {"tMs": 7572, "lane": 0}, {"tMs": 7634, "lane": 0}, {"tMs": 7696, "lane": 2}, {"tMs": 7758, "lane": 0}, {"tMs": 7820, "lane": 3}, {"tMs": 7882, "lane": 3}, {"tMs": 7944, "lane": 0}, {"tMs": 8006, "lane": 0}, {"tMs": 8068, "lane": 2}, {"tMs": 8130, "lane": 3}, {"tMs": 8192, "lane": 2}, {"tMs": 8254, "lane": 2}, {"tMs": 8316, "lane": 2}, {"tMs": 8378, "lane": 0}, {"tMs": 8440, "lane": 3}, {"tMs": 8502, "lane": 0}, {"tMs": 8564, "lane": 0}, {"tMs": 8626, "lane": 1}, {"tMs": 8688, "lane": 3}, {"tMs": 8750, "lane": 1}, {"tMs": 8812, "lane": 3}, {"tMs": 8874, "lane": 3}, {"tMs": 8936, "lane": 3}, {"tMs": 8998, "lane": 0}, {"tMs": 9060, "lane": 2}, {"tMs": 9122, "lane": 2}, {"tMs": 9184, "lane": 0}, {"tMs": 9246, "lane": 3}, {"tMs": 9308, "lane": 2}, {"tMs": 9370, "lane": 0}, {"tMs": 9432, "lane": 3}, {"tMs": 9494, "lane": 1}, {"tMs": 9556, "lane": 2}, {"tMs": 9618, "lane": 0}, {"tMs": 9680, "lane": 3}, {"tMs": 9742, "lane": 0}, {"tMs": 9804, "lane": 3}, {"tMs": 9866, "lane": 2}, {"tMs": 9928, "lane": 3}, {"tMs": 9990, "lane": 1}, {"tMs": 10052, "lane": 2}, {"tMs": 10114, "lane": 3}, {"tMs": 10176, "lane": 1}, {"tMs": 10238, "lane": 0}, {"tMs": 10300, "lane": 3}, {"tMs": 10362, "lane": 3}, {"tMs": 10424, "lane": 3}, {"tMs": 10486, "lane": 1}, {"tMs": 10548, "lane": 2}, {"tMs": 10610, "lane": 2}, {"tMs": 10672, "lane": 2}, {"tMs": 10734, "lane": 1}, {"tMs": 10796, "lane": 0}, {"tMs": 10858, "lane": 2}, {"tMs": 10920, "lane": 3}, {"tMs": 10982, "lane": 2}, {"tMs": 11044, "lane": 2}, {"tMs": 11106, "lane": 2}, {"tMs": 11168, "lane": 1}, {"tMs": 11230, "lane": 3}, {"tMs": 11292, "lane": 0}, {"tMs": 11354, "lane": 3}, {"tMs": 11416, "lane": 2}, {"tMs": 11478, "lane": 1}, {"tMs": 11540, "lane": 0}, {"tMs": 11602, "lane": 2}, {"tMs": 11664, "lane": 1}, {"tMs": 11726, "lane": 3}, {"tMs": 11788, "lane": 1}, {"tMs": 11850, "lane": 3}, {"tMs": 11912, "lane": 0}, {"tMs": 11974, "lane": 0}, {"tMs": 12036, "lane": 0}, {"tMs": 12098, "lane": 3}, {"tMs": 12160, "lane": 1}, {"tMs": 12222, "lane": 3}, {"tMs": 12284, "lane": 0}, {"tMs": 12346, "lane": 0}, {"tMs": 12408, "lane": 3}, {"tMs": 12470, "lane": 1}, {"tMs": 12532, "lane": 0}, {"tMs": 12594, "lane": 3}, {"tMs": 12656, "lane": 3}, {"tMs": 12718, "lane": 1}, {"tMs": 12780, "lane": 1}, {"tMs": 12842, "lane": 3}, {"tMs": 12904, "lane": 3}, {"tMs": 12966, "lane": 0}, {"tMs": 13028, "lane": 1}, {"tMs": 13090, "lane": 2}, {"tMs": 13152, "lane": 3}, {"tMs": 13214, "lane": 1}, {"tMs": 13276, "lane": 1}, {"tMs": 13338, "lane": 2}, {"tMs": 13400, "lane": 3}, {"tMs": 13462, "lane": 2}, {"tMs": 13524, "lane": 1}, {"tMs": 13586, "lane": 3}, {"tMs": 13648, "lane": 0}, {"tMs": 13710, "lane": 3}, {"tMs": 13772, "lane": 3}, {"tMs": 13834, "lane": 2}, {"tMs": 13896, "lane": 2}, {"tMs": 13958, "lane": 2}, {"tMs": 14020, "lane": 2}, {"tMs": 14082, "lane": 2}, {"tMs": 14144, "lane": 1}, {"tMs": 14206, "lane": 2}, {"tMs": 14268, "lane": 3}, {"tMs": 14330, "lane": 0}, {"tMs": 14392, "lane": 3}, {"tMs": 14454, "lane": 2}, {"tMs": 14516, "lane": 1}, {"tMs": 14578, "lane": 0}, {"tMs": 14640, "lane": 1}, {"tMs": 14702, "lane": 2}, {"tMs": 14764, "lane": 0}, {"tMs": 14826, "lane": 0}, {"tMs": 14888, "lane": 3}, {"tMs": 14950, "lane": 3}, {"tMs": 15012, "lane": 3}, {"tMs": 15074, "lane": 1}, {"tMs": 15136, "lane": 2}, {"tMs": 15198, "lane": 2}, {"tMs": 15260, "lane": 0}, {"tMs": 15322, "lane": 0}, {"tMs": 15384, "lane": 1}, {"tMs": 15446, "lane": 2}, {"tMs": 15508, "lane": 1}, {"tMs": 15570, "lane": 0}, {"tMs": 15632, "lane": 0}, {"tMs": 15694, "lane": 3}, {"tMs": 15756, "lane": 0}, {"tMs": 15818, "lane": 1}, {"tMs": 15880, "lane": 1}, {"tMs": 15942, "lane": 0}, {"tMs": 16004, "lane": 0}, {"tMs": 16066, "lane": 0}, {"tMs": 16128, "lane": 3}, {"tMs": 16190, "lane": 2}, {"tMs": 16252, "lane": 2}, {"tMs": 16314, "lane": 2}, {"tMs": 16376, "lane": 0}, {"tMs": 16438, "lane": 2}, {"tMs": 16500, "lane": 1}, {"tMs": 16562, "lane": 0}, {"tMs": 16624, "lane": 0}, {"tMs": 16686, "lane": 0}, {"tMs": 16748, "lane": 2}, {"tMs": 16810, "lane": 1}, {"tMs": 16872, "lane": 3}, {"tMs": 16934, "lane": 3}, {"tMs": 16996, "lane": 0}, {"tMs": 17058, "lane": 3}, {"tMs": 17120, "lane": 3}, {"tMs": 17182, "lane": 1}, {"tMs": 17244, "lane": 1}, {"tMs": 17306, "lane": 1}, {"tMs": 17368, "lane": 1}, {"tMs": 17430, "lane": 1}, {"tMs": 17492, "lane": 3}, {"tMs": 17554, "lane": 2}, {"tMs": 17616, "lane": 2}, {"tMs": 17678, "lane": 3}, {"tMs": 17740, "lane": 0}, {"tMs": 17802, "lane": 0}, {"tMs": 17864, "lane": 1}, {"tMs": 17926, "lane": 3}, {"tMs": 17988, "lane": 0}, {"tMs": 18050, "lane": 3}, {"tMs": 18112, "lane": 1}, {"tMs": 18174, "lane": 1}, {"tMs": 18236, "lane": 2}, {"tMs": 18298, "lane": 2}, {"tMs": 18360, "lane": 1}, {"tMs": 18422, "lane": 0}, {"tMs": 18484, "lane": 0}, {"tMs": 18546, "lane": 0}, {"tMs": 18608, "lane": 1}, {"tMs": 18670, "lane": 1}, {"tMs": 18732, "lane": 2}, {"tMs": 18794, "lane": 2}, {"tMs": 18856, "lane": 3}, {"tMs": 18918, "lane": 2}, {"tMs": 18980, "lane": 3}]}